artifact_generator-2.0.0.data/scripts/gen
generators/__init__.py
generators/generate.py
generators/template.py
generators/util/__init__.py
generators/util/file_manager.py
generators/util/generator_path.py
generators/util/namespaces.py
generators/util/ontology_reader.py
generators/util/rdf2json.py
artifact_generator-2.0.0.dist-info/LICENSE
artifact_generator-2.0.0.dist-info/METADATA
artifact_generator-2.0.0.dist-info/WHEEL
artifact_generator-2.0.0.dist-info/top_level.txt
artifact_generator-2.0.0.dist-info/RECORD
