Metadata-Version: 2.1
Name: artifact-generator
Version: 2.0.0
Summary: Tool for generating assets from rdf model.
Home-page: https://github.com/dfriedenberger/generators.git
Author: Dirk Friedenberger
Author-email: projekte@frittenburger.de
License: GPLv3
License-File: LICENSE
Requires-Dist: chevron
Requires-Dist: rdflib
Requires-Dist: obse
